apollo/__init__.py
apollo/apollo_client.py
apollo/python_2x.py
apollo/python_3x.py
apollo/util.py
xx_apollo-2023.7.14.17.23.16.dist-info/METADATA
xx_apollo-2023.7.14.17.23.16.dist-info/WHEEL
xx_apollo-2023.7.14.17.23.16.dist-info/top_level.txt
xx_apollo-2023.7.14.17.23.16.dist-info/RECORD
