Metadata-Version: 2.1
Name: xx-apollo
Version: 2023.7.14.17.23.16
Summary: Create a Python package.
Home-page: 
Author: yuanjie
Author-email: 313303303@qq.com
License: MIT license
Keywords: xx-apollo
Classifier: Development Status :: 2 - Pre-Alpha
Classifier: Intended Audience :: Developers
Classifier: License :: OSI Approved :: MIT License
Classifier: Natural Language :: English
Classifier: Programming Language :: Python :: 3.7
Classifier: Programming Language :: Python :: 3.8
Requires-Python: >=3.7
